README.rst
setup.py
pyvadc/__init__.py
pyvadc/bsd.py
pyvadc/config.py
pyvadc/vadc.py
pyvadc/vtm.py
pyvadc.egg-info/PKG-INFO
pyvadc.egg-info/SOURCES.txt
pyvadc.egg-info/dependency_links.txt
pyvadc.egg-info/requires.txt
pyvadc.egg-info/top_level.txt